lumett/__init__.py
lumett/cli.py
lumett/data/LICENSE
lumett/data/README.txt
lumett/data/lumett.ico
lumett/data/lumett.png
lumett/data/lib/colors.tin
lumett/data/lib/filesystem.tin
lumett/data/lib/init.tin
lumett/data/lib/modloader.tin
lumett/data/lib/wizard.tin
lumett/data/lib/wizard2.tin
lumett/data/lib/wizard_dirs_python.tin
lumett/data/mintty/mintty_wcli_rc
lumett/data/mintty/minttyrc
lumett/data/mintty/usr/share/mintty/emojis/getemojis
lumett/data/mintty/usr/share/mintty/icon/wsl.ico
lumett/data/mintty/usr/share/mintty/lang/de.po
lumett/data/mintty/usr/share/mintty/lang/en.po
lumett/data/mintty/usr/share/mintty/lang/en_US.po
lumett/data/mintty/usr/share/mintty/lang/es.po
lumett/data/mintty/usr/share/mintty/lang/fr.po
lumett/data/mintty/usr/share/mintty/lang/hr.po
lumett/data/mintty/usr/share/mintty/lang/ja.po
lumett/data/mintty/usr/share/mintty/lang/messages.pot
lumett/data/mintty/usr/share/mintty/lang/nb.po
lumett/data/mintty/usr/share/mintty/lang/pt_BR.po
lumett/data/mintty/usr/share/mintty/lang/ru.po
lumett/data/mintty/usr/share/mintty/lang/sv.po
lumett/data/mintty/usr/share/mintty/lang/zh_CN.po
lumett/data/mintty/usr/share/mintty/lang/zh_TW.po
lumett/data/mintty/usr/share/mintty/sounds/BOING.WAV
lumett/data/mintty/usr/share/mintty/sounds/README.md
lumett/data/mintty/usr/share/mintty/sounds/ambient-drip-lo.wav
lumett/data/mintty/usr/share/mintty/sounds/ambient-drop.wav
lumett/data/mintty/usr/share/mintty/sounds/ambient-glass.wav
lumett/data/mintty/usr/share/mintty/sounds/ambient-splash.wav
lumett/data/mintty/usr/share/mintty/sounds/ambient-swoosh.wav
lumett/data/mintty/usr/share/mintty/sounds/ambient-uncork.wav
lumett/data/mintty/usr/share/mintty/sounds/percussive-bongo-hi.wav
lumett/data/mintty/usr/share/mintty/sounds/percussive-bongo-lo.wav
lumett/data/mintty/usr/share/mintty/sounds/percussive-gong.wav
lumett/data/mintty/usr/share/mintty/sounds/percussive-knock.wav
lumett/data/mintty/usr/share/mintty/sounds/percussive-synthkick-lo.wav
lumett-2.0.6.dist-info/METADATA
lumett-2.0.6.dist-info/WHEEL
lumett-2.0.6.dist-info/entry_points.txt
lumett-2.0.6.dist-info/top_level.txt
lumett-2.0.6.dist-info/RECORD
